python_generator/cli.py
python_generator/templates.py
project_generator_python-0.1.2.dist-info/METADATA
project_generator_python-0.1.2.dist-info/WHEEL
project_generator_python-0.1.2.dist-info/entry_points.txt
project_generator_python-0.1.2.dist-info/top_level.txt
project_generator_python-0.1.2.dist-info/RECORD
