Metadata-Version: 2.1
Name: project-generator-python
Version: 0.1.2
Summary: A CLI tool to generate Python projects with various templates
Author-email: barryduan <duanyongcheng77@gmail.com>
License: MIT
Project-URL: Homepage, https://github.com/duanyongcheng/flask-project-generator
Project-URL: Repository, https://github.com/duanyongcheng/flask-project-generator.git
Requires-Python: >=3.8
Requires-Dist: click
Requires-Dist: questionary
Requires-Dist: python-dotenv
